pyqrc/__init__.py
pyqrc/__main__.py
pyqrc/pyQRC.py
pyqrc-2.1.0.dist-info/licenses/LICENSE
pyqrc-2.1.0.dist-info/METADATA
pyqrc-2.1.0.dist-info/WHEEL
pyqrc-2.1.0.dist-info/entry_points.txt
pyqrc-2.1.0.dist-info/top_level.txt
pyqrc-2.1.0.dist-info/RECORD
