Metadata-Version: 2.4
Name: pyqrc
Version: 2.1.0
Summary: A Python program to project computed structures along normal modes for Quick Reaction Coordinate calculations
Author-email: Paton Research Group <patonlab@colostate.edu>
Maintainer-email: Robert Paton <robert.paton@colostate.edu>
License: MIT
Project-URL: Homepage, https://github.com/patonlab/pyQRC
Project-URL: Repository, https://github.com/patonlab/pyQRC
Project-URL: Documentation, https://github.com/patonlab/pyQRC#readme
Project-URL: Issues, https://github.com/patonlab/pyQRC/issues
Keywords: computational-chemistry,thermochemistry,gaussian,orca,qchem,imaginary-frequencies,intrinsic-reaction-coordinate,normal-modes,transition-state
Classifier: Development Status :: 5 - Production/Stable
Classifier: Intended Audience :: Science/Research
Classifier: License :: OSI Approved :: MIT License
Classifier: Operating System :: OS Independent
Classifier: Programming Language :: Python :: 3
Classifier: Programming Language :: Python :: 3.9
Classifier: Programming Language :: Python :: 3.10
Classifier: Programming Language :: Python :: 3.11
Classifier: Programming Language :: Python :: 3.12
Classifier: Topic :: Scientific/Engineering :: Chemistry
Requires-Python: >=3.9
License-File: LICENSE
Requires-Dist: cclib
Requires-Dist: numpy
Provides-Extra: dev
Requires-Dist: pytest>=7.0; extra == "dev"
Requires-Dist: pytest-cov; extra == "dev"
Requires-Dist: pylint>=3.0; extra == "dev"
Dynamic: license-file
